LICENSE.md
MANIFEST.in
README.md
setup.py
pddlgymnasium/__init__.py
pddlgymnasium/core.py
pddlgymnasium/demo.py
pddlgymnasium/demo_planning.py
pddlgymnasium/inference.py
pddlgymnasium/parser.py
pddlgymnasium/prolog_interface.py
pddlgymnasium/spaces.py
pddlgymnasium/structs.py
pddlgymnasium/utils.py
pddlgymnasium.egg-info/PKG-INFO
pddlgymnasium.egg-info/SOURCES.txt
pddlgymnasium.egg-info/dependency_links.txt
pddlgymnasium.egg-info/requires.txt
pddlgymnasium.egg-info/top_level.txt
pddlgymnasium/custom/__init__.py
pddlgymnasium/custom/searchandrescue.py
pddlgymnasium/downward_translate/__init__.py
pddlgymnasium/downward_translate/axiom_rules.py
pddlgymnasium/downward_translate/build_model.py
pddlgymnasium/downward_translate/constraints.py
pddlgymnasium/downward_translate/fact_groups.py
pddlgymnasium/downward_translate/graph.py
pddlgymnasium/downward_translate/greedy_join.py
pddlgymnasium/downward_translate/instantiate.py
pddlgymnasium/downward_translate/invariant_finder.py
pddlgymnasium/downward_translate/invariants.py
pddlgymnasium/downward_translate/normalize.py
pddlgymnasium/downward_translate/options.py
pddlgymnasium/downward_translate/pddl_to_prolog.py
pddlgymnasium/downward_translate/sas_tasks.py
pddlgymnasium/downward_translate/sccs.py
pddlgymnasium/downward_translate/simplify.py
pddlgymnasium/downward_translate/split_rules.py
pddlgymnasium/downward_translate/timers.py
pddlgymnasium/downward_translate/tools.py
pddlgymnasium/downward_translate/translate.py
pddlgymnasium/downward_translate/variable_order.py
pddlgymnasium/downward_translate/pddl/__init__.py
pddlgymnasium/downward_translate/pddl/actions.py
pddlgymnasium/downward_translate/pddl/axioms.py
pddlgymnasium/downward_translate/pddl/conditions.py
pddlgymnasium/downward_translate/pddl/effects.py
pddlgymnasium/downward_translate/pddl/f_expression.py
pddlgymnasium/downward_translate/pddl/functions.py
pddlgymnasium/downward_translate/pddl/pddl_types.py
pddlgymnasium/downward_translate/pddl/predicates.py
pddlgymnasium/downward_translate/pddl/tasks.py
pddlgymnasium/downward_translate/pddl_parser/__init__.py
pddlgymnasium/downward_translate/pddl_parser/lisp_parser.py
