Metadata-Version: 2.1
Name: pddlgymnasium
Version: 0.0.2
Summary: Gym environment based PDDL problem description
Requires-Python: >=3.8
License-File: LICENSE.md
Requires-Dist: matplotlib
Requires-Dist: pillow<10,>=8
Requires-Dist: gymnasium<1.0.0
Requires-Dist: imageio
Requires-Dist: networkx
Requires-Dist: scikit-image
